cc_agency/__init__.py
cc_agency/broker/__init__.py
cc_agency/broker/app.py
cc_agency/broker/auth.py
cc_agency/broker/jwt_token.py
cc_agency/broker/routes/__init__.py
cc_agency/broker/routes/nodes.py
cc_agency/broker/routes/red.py
cc_agency/commons/__init__.py
cc_agency/commons/cloud_proxy.py
cc_agency/commons/conf.py
cc_agency/commons/db.py
cc_agency/commons/helper.py
cc_agency/commons/schemas/__init__.py
cc_agency/commons/schemas/callback.py
cc_agency/commons/schemas/conf.py
cc_agency/commons/secrets.py
cc_agency/controller/__init__.py
cc_agency/controller/__main__.py
cc_agency/controller/docker.py
cc_agency/controller/main.py
cc_agency/controller/scheduler.py
cc_agency/tools/__init__.py
cc_agency/tools/__main__.py
cc_agency/tools/create_broker_user/__init__.py
cc_agency/tools/create_broker_user/__main__.py
cc_agency/tools/create_broker_user/main.py
cc_agency/tools/create_db_user/__init__.py
cc_agency/tools/create_db_user/__main__.py
cc_agency/tools/create_db_user/main.py
cc_agency/tools/drop_db_collections/__init__.py
cc_agency/tools/drop_db_collections/__main__.py
cc_agency/tools/drop_db_collections/main.py
cc_agency/tools/main.py
cc_agency/trustee/__init__.py
cc_agency/trustee/app.py
cc_agency/version.py
cc_agency-9.3.0.dist-info/LICENSE
cc_agency-9.3.0.dist-info/METADATA
cc_agency-9.3.0.dist-info/WHEEL
cc_agency-9.3.0.dist-info/entry_points.txt
cc_agency-9.3.0.dist-info/RECORD
