Metadata-Version: 2.1
Name: cc-agency
Version: 9.3.0
Summary: CC-Agency is part of the Curious Containers project. It connects to a cluster of docker-engines for the distributed execution of reproducible data-driven experiments defined in the RED format.
Home-page: https://www.curious-containers.cc/
License: AGPL-3.0
Author: Christoph Jansen
Author-email: Christoph.Jansen@htw-berlin.de
Requires-Python: >=3.7,<4.0
Classifier: License :: OSI Approved :: GNU Affero General Public License v3
Classifier: Programming Language :: Python :: 3
Classifier: Programming Language :: Python :: 3.7
Classifier: Programming Language :: Python :: 3.8
Classifier: Programming Language :: Python :: 3.9
Classifier: Programming Language :: Python :: 3.10
Classifier: Programming Language :: Python :: 3.11
Requires-Dist: Werkzeug (>=2.2.3,<3.0.0)
Requires-Dist: cc-core (>=9.3,<9.4)
Requires-Dist: cryptography (>=41.0,<42.0)
Requires-Dist: filelock (>=3.12.2,<4.0.0)
Requires-Dist: flask (>=2.2,<3.0)
Requires-Dist: flask-cors (>=4.0.0,<5.0.0)
Requires-Dist: flask-jwt-extended (>=4.5.2,<5.0.0)
Requires-Dist: pymongo (>=3.7,<4.0)
Requires-Dist: pyzmq (>=23.0,<24.0)
Requires-Dist: urllib3 (>=1.26,<2.0)
Project-URL: Repository, https://github.com/curious-containers/cc-agency
